automlu/__init__.py
automlu/hyper_param_optimizer.py
automlu/slicer.py
auto_mlu-0.3.0.dist-info/LICENSE
auto_mlu-0.3.0.dist-info/METADATA
auto_mlu-0.3.0.dist-info/WHEEL
auto_mlu-0.3.0.dist-info/top_level.txt
auto_mlu-0.3.0.dist-info/RECORD
